apispreadsheets_lib/__init__.py
apispreadsheets_lib/client.py
apispreadsheets_lib-1.0.0.dist-info/METADATA
apispreadsheets_lib-1.0.0.dist-info/WHEEL
apispreadsheets_lib-1.0.0.dist-info/licenses/LICENSE
apispreadsheets_lib-1.0.0.dist-info/RECORD
