Metadata-Version: 2.4
Name: apispreadsheets-lib
Version: 1.0.0
Summary: Python client for API Spreadsheets (Official Library)
Project-URL: Homepage, https://www.apispreadsheets.com
Project-URL: Issues, https://www.apispreadsheets.com/contact
Author-email: API Spreadsheets <info@apispreadsheets.com>
License: MIT License
License-File: LICENSE
Keywords: api,apispreadsheets,automation,csv,excel,spreadsheets
Requires-Python: >=3.8
Requires-Dist: requests<3.0,>=2.28
